[
    {
        "title": "sex.lies.murder.fame",
        "subject": [
            "Publishers and publishing",
            "Fiction",
            "Romance",
            "Music trade",
            "Fiction, psychological",
            "Publishers and publishing, fiction",
            "New york (n.y.), fiction"
        ],
        "authors": [
            "Lolita Files"
        ],
        "publish_year": 2006
    },
    {
        "title": "Strange Rapture",
        "subject": [
            "1930s",
            "Contemporary",
            "English",
            "Fiction",
            "Love Triangle",
            "Romance",
            "Fiction in English"
        ],
        "authors": [
            "Denise Robins"
        ],
        "publish_year": 1932
    },
    {
        "title": "Brief Ecstasy",
        "subject": [
            "1930s",
            "Contemporary",
            "English",
            "Fiction",
            "Love triangle",
            "Romance"
        ],
        "authors": [
            "Denise Robins"
        ],
        "publish_year": 1934
    },
    {
        "title": "Treasured Vows",
        "subject": [
            "Love stories",
            "Fiction",
            "Guardian and ward",
            "Fathers and daughters",
            "Inheritance and succession",
            "Explorers",
            "Romance",
            "Fiction, romance, historical",
            "Large type books",
            "Fiction, romance, historical, general"
        ],
        "authors": [
            "Cathy Maxwell"
        ],
        "publish_year": 1996
    },
    {
        "title": "Songs in ordinary time",
        "subject": [
            "Fiction",
            "Divorced women",
            "Problem families",
            "Romance",
            "Vermont -- Fiction",
            "Dysfunctional families",
            "Vermont, fiction",
            "Fermoyle, marie (fictitious character), fiction",
            "Fiction, family life, general",
            "Romans, nouvelles",
            "Fiction, general"
        ],
        "authors": [
            "Mary McGarry Morris"
        ],
        "publish_year": 1995
    },
    {
        "title": "The Ultimate Betrayal",
        "subject": [
            "Fiction, romance, general",
            "Fiction, Romance, Contemporary",
            "Large print books",
            "Large type books",
            "Fiction",
            "Adultery",
            "Love stories",
            "romance",
            "Harlequin"
        ],
        "authors": [
            "Michelle Reid"
        ],
        "publish_year": 1995
    },
    {
        "title": "The Feast is Finished",
        "subject": [
            "1940s",
            "Contemporary",
            "English",
            "Fiction",
            "Love Triangle",
            "Romance",
            "Large type books"
        ],
        "authors": [
            "Denise Robins"
        ],
        "publish_year": 1948
    },
    {
        "title": "The Vision",
        "subject": [
            "Romantic suspense",
            "Open Library Staff Picks",
            "Crimes against",
            "Fiction",
            "Romance",
            "Treasure troves",
            "Suspense",
            "Serial murderers",
            "Thriller",
            "Women",
            "Fiction, romance, fantasy",
            "Fiction, thrillers, general",
            "Fiction, psychological",
            "Large type books",
            "Fiction, romance, paranormal",
            "Fiction, romance, suspense",
            "Florida, fiction",
            "Fiction, ghost",
            "Fiction, suspense",
            "Criminals, fiction",
            "Fiction, romance, paranormal, general",
            "Fiction, thrillers, suspense"
        ],
        "authors": [
            "Heather Graham"
        ],
        "publish_year": 2006
    },
    {
        "title": "Now You See Her",
        "subject": [
            "Fiction",
            "Women artists",
            "Romance",
            "Romantic suspense",
            "dreams",
            "Sweeney, paris (fictitious character), fiction",
            "Fiction, thrillers, suspense",
            "Fiction, psychological",
            "New york (n.y.), fiction",
            "Fiction, romance, contemporary",
            "Women artists, fiction"
        ],
        "authors": [
            "Linda Howard"
        ],
        "publish_year": 1998
    },
    {
        "title": "Sarah's Child",
        "subject": [
            "Romance",
            "Contemporary Romance",
            "Fiction",
            "Infants",
            "Widowers",
            "Fiction, romance, general",
            "Large type books"
        ],
        "authors": [
            "Linda Howard"
        ],
        "publish_year": 1985
    },
    {
        "title": "Amberwell (Ayrton Family #1)",
        "subject": [
            "Fiction",
            "Romantic Fiction",
            "Romance",
            "Fiction, general"
        ],
        "authors": [
            "D. E. Stevenson"
        ],
        "publish_year": 1955
    },
    {
        "title": "White Mughals",
        "subject": [
            "Social life and customs",
            "Race relations",
            "Outlook of Empire",
            "British",
            "Romance",
            "Social mores",
            "History",
            "India, race relations",
            "British, india",
            "India, history, british occupation, 1765-1947",
            "India, social life and customs",
            "Fiction",
            "Afghan Wars",
            "15.75 history of Asia",
            "Fiction, historical, general",
            "Afghanistan, fiction",
            "History of asia",
            "Britanniques",
            "Histoire",
            "India, history, 19th century",
            "Great Britain. Army"
        ],
        "authors": [
            "William Dalrymple"
        ],
        "publish_year": 2002
    },
    {
        "title": "The Ultimate Betrayal",
        "subject": [
            "Fiction, romance, general",
            "Fiction, Romance, Contemporary",
            "Large print books",
            "Large type books",
            "Fiction",
            "Adultery",
            "Love stories",
            "romance",
            "Harlequin"
        ],
        "authors": [
            "Michelle Reid"
        ],
        "publish_year": 1995
    },
    {
        "title": "The Feast is Finished",
        "subject": [
            "1940s",
            "Contemporary",
            "English",
            "Fiction",
            "Love Triangle",
            "Romance",
            "Large type books"
        ],
        "authors": [
            "Denise Robins"
        ],
        "publish_year": 1948
    },
    {
        "title": "The Vision",
        "subject": [
            "Romantic suspense",
            "Open Library Staff Picks",
            "Crimes against",
            "Fiction",
            "Romance",
            "Treasure troves",
            "Suspense",
            "Serial murderers",
            "Thriller",
            "Women",
            "Fiction, romance, fantasy",
            "Fiction, thrillers, general",
            "Fiction, psychological",
            "Large type books",
            "Fiction, romance, paranormal",
            "Fiction, romance, suspense",
            "Florida, fiction",
            "Fiction, ghost",
            "Fiction, suspense",
            "Criminals, fiction",
            "Fiction, romance, paranormal, general",
            "Fiction, thrillers, suspense"
        ],
        "authors": [
            "Heather Graham"
        ],
        "publish_year": 2006
    },
    {
        "title": "Now You See Her",
        "subject": [
            "Fiction",
            "Women artists",
            "Romance",
            "Romantic suspense",
            "dreams",
            "Sweeney, paris (fictitious character), fiction",
            "Fiction, thrillers, suspense",
            "Fiction, psychological",
            "New york (n.y.), fiction",
            "Fiction, romance, contemporary",
            "Women artists, fiction"
        ],
        "authors": [
            "Linda Howard"
        ],
        "publish_year": 1998
    },
    {
        "title": "Sarah's Child",
        "subject": [
            "Romance",
            "Contemporary Romance",
            "Fiction",
            "Infants",
            "Widowers",
            "Fiction, romance, general",
            "Large type books"
        ],
        "authors": [
            "Linda Howard"
        ],
        "publish_year": 1985
    },
    {
        "title": "Amberwell (Ayrton Family #1)",
        "subject": [
            "Fiction",
            "Romantic Fiction",
            "Romance",
            "Fiction, general"
        ],
        "authors": [
            "D. E. Stevenson"
        ],
        "publish_year": 1955
    },
    {
        "title": "White Mughals",
        "subject": [
            "Social life and customs",
            "Race relations",
            "Outlook of Empire",
            "British",
            "Romance",
            "Social mores",
            "History",
            "India, race relations",
            "British, india",
            "India, history, british occupation, 1765-1947",
            "India, social life and customs",
            "Fiction",
            "Afghan Wars",
            "15.75 history of Asia",
            "Fiction, historical, general",
            "Afghanistan, fiction",
            "History of asia",
            "Britanniques",
            "Histoire",
            "India, history, 19th century",
            "Great Britain. Army"
        ],
        "authors": [
            "William Dalrymple"
        ],
        "publish_year": 2002
    },
    {
        "title": "The homecoming",
        "subject": [
            "Self-actualization (Psychology)",
            "Life change events",
            "Homecoming",
            "Fiction",
            "Fiction, romance, contemporary",
            "Fiction, sports",
            "nyt:mass-market-paperback=2014-09-14",
            "New York Times bestseller",
            "Large type books",
            "FICTION / Romance / Contemporary",
            "Romance",
            "Contemporary",
            "Fiction, general",
            "nyt:combined-print-and-e-book-fiction=2014-09-14"
        ],
        "authors": [
            "Robyn Carr"
        ],
        "publish_year": 2014
    },
    {
        "title": "Confessions of a Jane Austen Addict",
        "subject": [
            "Social life and customs",
            "Man-woman relationships",
            "Literature",
            "Single women",
            "Influence",
            "Fiction",
            "Romance",
            "Humor (Fiction)",
            "Time travel",
            "Love stories",
            "Fiction, romance, fantasy",
            "Austen, jane, 1775-1817, fiction",
            "Large type books",
            "Single women, fiction",
            "Fiction, fantasy, general",
            "Fiction, romance, time travel",
            "Great britain, fiction"
        ],
        "authors": [
            "Laurie Viera Rigler"
        ],
        "publish_year": 2007
    },
    {
        "title": "The Peacock Emporium",
        "subject": [
            "Mothers and daughters",
            "Fiction",
            "Community life",
            "Madre e hija",
            "Vida en comunidad",
            "Ficcion",
            "Women",
            "Coffee shops",
            "Contemporary Women",
            "Romance",
            "General",
            "Contemporary",
            "Families",
            "Mother-daughter relationship",
            "Specialty stores",
            "Restaurants",
            "Fiction, general",
            "Mothers and daughters, fiction",
            "Mothers and daughters -- Fiction",
            "Community life -- England -- Fiction",
            "Madre e hija -- Ficcion",
            "Vida en comunidad -- Ficcion",
            "England -- Fiction",
            "Inglaterra -- Ficcion"
        ],
        "authors": [
            "Jojo Moyes"
        ],
        "publish_year": 2004
    },
    {
        "title": "Novels (Dance to the Piper / Last Honest Woman)",
        "subject": [
            "Biographers",
            "Women dancers",
            "Triplets",
            "Hurley family",
            "Fiction",
            "Businessmen",
            "Automobile racing drivers' spouses",
            "Widows",
            "Love stories, American",
            "Fiction, romance, contemporary",
            "Fiction, sagas",
            "Large type books",
            "Man-woman relationships",
            "Journalists",
            "Dancers",
            "Widows, fiction",
            "Romance",
            "nyt:mass-market-paperback=2010-10-31",
            "New York Times bestseller"
        ],
        "authors": [
            "Nora Roberts"
        ],
        "publish_year": 2004
    },
    {
        "title": "Our Souls at Night",
        "subject": [
            "Widowers",
            "Fiction",
            "Loneliness",
            "Grandparent and child",
            "Memory",
            "Romance fiction",
            "Domestic fiction",
            "Large type books",
            "Colorado, fiction",
            "Fiction, romance, general",
            "FICTION / Family Life",
            "FICTION / Romance / General",
            "FICTION / Literary",
            "Older people",
            "Widows",
            "Fellowship",
            "Family life",
            "Grief",
            "Emotions",
            "Romance",
            "General",
            "Literary",
            "nyt:hardcover-fiction=2015-06-14",
            "New York Times bestseller",
            "New York Times reviewed",
            "Fiction, family life",
            "Fiction, romance, contemporary",
            "Widowers, fiction",
            "Man-woman relationships, fiction",
            "Fiction, family life, general",
            "(Produktform)Hardback",
            "Alter",
            "Amerika",
            "Amerikaner",
            "Bewegend",
            "Colorado",
            "Einsamkeit",
            "Enkel",
            "Fonda, Jane",
            "Gespra\u0308che",
            "Holt",
            "Hunde",
            "Kind",
            "Klatschmohnfrau",
            "Kleinstadt",
            "Lehrer",
            "Liebe",
            "Liebesgeschichte",
            "Redford, Robert",
            "Senioren",
            "Stoner",
            "USA",
            "Verfilmung",
            "amerikanische Literatur",
            "best agers",
            "spa\u0308te",
            "A\u0308lterwerden",
            "(VLB-WN)1112: Hardcover, Softcover / Belletristik/Gegenwartsliteratur (ab 1945)"
        ],
        "authors": [
            "Kent Haruf"
        ],
        "publish_year": 2015
    },
    {
        "title": "Amberwell (Ayrton Family #1)",
        "subject": [
            "Fiction",
            "Romantic Fiction",
            "Romance",
            "Fiction, general"
        ],
        "authors": [
            "D. E. Stevenson"
        ],
        "publish_year": 1955
    },
    {
        "title": "White Mughals",
        "subject": [
            "Social life and customs",
            "Race relations",
            "Outlook of Empire",
            "British",
            "Romance",
            "Social mores",
            "History",
            "India, race relations",
            "British, india",
            "India, history, british occupation, 1765-1947",
            "India, social life and customs",
            "Fiction",
            "Afghan Wars",
            "15.75 history of Asia",
            "Fiction, historical, general",
            "Afghanistan, fiction",
            "History of asia",
            "Britanniques",
            "Histoire",
            "India, history, 19th century",
            "Great Britain. Army"
        ],
        "authors": [
            "William Dalrymple"
        ],
        "publish_year": 2002
    },
    {
        "title": "The homecoming",
        "subject": [
            "Self-actualization (Psychology)",
            "Life change events",
            "Homecoming",
            "Fiction",
            "Fiction, romance, contemporary",
            "Fiction, sports",
            "nyt:mass-market-paperback=2014-09-14",
            "New York Times bestseller",
            "Large type books",
            "FICTION / Romance / Contemporary",
            "Romance",
            "Contemporary",
            "Fiction, general",
            "nyt:combined-print-and-e-book-fiction=2014-09-14"
        ],
        "authors": [
            "Robyn Carr"
        ],
        "publish_year": 2014
    },
    {
        "title": "Confessions of a Jane Austen Addict",
        "subject": [
            "Social life and customs",
            "Man-woman relationships",
            "Literature",
            "Single women",
            "Influence",
            "Fiction",
            "Romance",
            "Humor (Fiction)",
            "Time travel",
            "Love stories",
            "Fiction, romance, fantasy",
            "Austen, jane, 1775-1817, fiction",
            "Large type books",
            "Single women, fiction",
            "Fiction, fantasy, general",
            "Fiction, romance, time travel",
            "Great britain, fiction"
        ],
        "authors": [
            "Laurie Viera Rigler"
        ],
        "publish_year": 2007
    },
    {
        "title": "The Peacock Emporium",
        "subject": [
            "Mothers and daughters",
            "Fiction",
            "Community life",
            "Madre e hija",
            "Vida en comunidad",
            "Ficcion",
            "Women",
            "Coffee shops",
            "Contemporary Women",
            "Romance",
            "General",
            "Contemporary",
            "Families",
            "Mother-daughter relationship",
            "Specialty stores",
            "Restaurants",
            "Fiction, general",
            "Mothers and daughters, fiction",
            "Mothers and daughters -- Fiction",
            "Community life -- England -- Fiction",
            "Madre e hija -- Ficcion",
            "Vida en comunidad -- Ficcion",
            "England -- Fiction",
            "Inglaterra -- Ficcion"
        ],
        "authors": [
            "Jojo Moyes"
        ],
        "publish_year": 2004
    },
    {
        "title": "Novels (Dance to the Piper / Last Honest Woman)",
        "subject": [
            "Biographers",
            "Women dancers",
            "Triplets",
            "Hurley family",
            "Fiction",
            "Businessmen",
            "Automobile racing drivers' spouses",
            "Widows",
            "Love stories, American",
            "Fiction, romance, contemporary",
            "Fiction, sagas",
            "Large type books",
            "Man-woman relationships",
            "Journalists",
            "Dancers",
            "Widows, fiction",
            "Romance",
            "nyt:mass-market-paperback=2010-10-31",
            "New York Times bestseller"
        ],
        "authors": [
            "Nora Roberts"
        ],
        "publish_year": 2004
    },
    {
        "title": "Our Souls at Night",
        "subject": [
            "Widowers",
            "Fiction",
            "Loneliness",
            "Grandparent and child",
            "Memory",
            "Romance fiction",
            "Domestic fiction",
            "Large type books",
            "Colorado, fiction",
            "Fiction, romance, general",
            "FICTION / Family Life",
            "FICTION / Romance / General",
            "FICTION / Literary",
            "Older people",
            "Widows",
            "Fellowship",
            "Family life",
            "Grief",
            "Emotions",
            "Romance",
            "General",
            "Literary",
            "nyt:hardcover-fiction=2015-06-14",
            "New York Times bestseller",
            "New York Times reviewed",
            "Fiction, family life",
            "Fiction, romance, contemporary",
            "Widowers, fiction",
            "Man-woman relationships, fiction",
            "Fiction, family life, general",
            "(Produktform)Hardback",
            "Alter",
            "Amerika",
            "Amerikaner",
            "Bewegend",
            "Colorado",
            "Einsamkeit",
            "Enkel",
            "Fonda, Jane",
            "Gespra\u0308che",
            "Holt",
            "Hunde",
            "Kind",
            "Klatschmohnfrau",
            "Kleinstadt",
            "Lehrer",
            "Liebe",
            "Liebesgeschichte",
            "Redford, Robert",
            "Senioren",
            "Stoner",
            "USA",
            "Verfilmung",
            "amerikanische Literatur",
            "best agers",
            "spa\u0308te",
            "A\u0308lterwerden",
            "(VLB-WN)1112: Hardcover, Softcover / Belletristik/Gegenwartsliteratur (ab 1945)"
        ],
        "authors": [
            "Kent Haruf"
        ],
        "publish_year": 2015
    },
    {
        "title": "Novels (Jane Eyre / Tenant of Wildfell Hall / Wuthering Heights)",
        "subject": [
            "British and irish fiction (fictional works by one author)",
            "Chang pian xiao shuo",
            "Children's fiction",
            "Classic fiction",
            "Classic Literature",
            "Country homes",
            "Country life",
            "Country life in fiction",
            "Cousins",
            "Cuentos de amor",
            "death",
            "Drama",
            "English language",
            "English language readers",
            "English literature: texts",
            "Families",
            "Ficci\u00f3n",
            "Fiction",
            "family life",
            "romance",
            "Foundlings",
            "Historical Fiction",
            "Inheritance and succession",
            "Interpersonal relations",
            "Landscape in literature",
            "love",
            "Man-woman relationships",
            "Manners and customs",
            "orphans",
            "Psychological fiction",
            "Reading Level-Grade 7",
            "Reading Level-Grade 8",
            "Reading Level-Grade 9",
            "Reading Level-Grade 10",
            "Reading Level-Grade 11",
            "Reading Level-Grade 12",
            "Rejection (Psychology)",
            "Relaciones hombre-mujer",
            "revenge",
            "Romance fiction",
            "romantic fiction",
            "Rural families",
            "slavery",
            "Social life and customs",
            "tragedy",
            "Triangles (Interpersonal relations)",
            "Young women",
            "English fiction",
            "Women authors",
            "Heathcliff (Fictitious character : Brontee)",
            "Edward Fairfax Rochester (Fictitious character)",
            "English literature (collections), 19th century"
        ],
        "authors": [
            "Anne Bront\u00eb",
            "Charlotte Bronte\u0308",
            "Emily Bronte\u0308"
        ],
        "publish_year": 1982
    },
    {
        "title": "Demelza",
        "subject": [
            "Ross Poldark (Fictitious character)",
            "Open Library Staff Picks",
            "Fiction",
            "Romance",
            "History",
            "Large type books",
            "English Historical fiction",
            "Fiction, historical, general",
            "Poldark, ross (fictitious character), fiction",
            "Cornwall (england : county), fiction",
            "Historical fiction, English",
            "Cornwall (England) -- Fiction"
        ],
        "authors": [
            "Winston Graham"
        ],
        "publish_year": 1953
    },
    {
        "title": "I'll Give You the Sun",
        "subject": [
            "Romance",
            "Young Adult",
            "Glbt",
            "Contemporary",
            "Fiction",
            "Coming of Age",
            "Death",
            "Families",
            "Brothers and sisters",
            "Juvenile fiction",
            "Family life",
            "Grief",
            "Twins",
            "Artists",
            "Gays",
            "Children's fiction",
            "Artists, fiction",
            "Twins, fiction",
            "Brothers and sisters, fiction",
            "Grief, fiction",
            "Death, fiction",
            "Family life, fiction",
            "California, fiction",
            "Homosexuality, fiction",
            "Mellizas",
            "Ficci\u00f3n juvenil",
            "Pena",
            "Muerte",
            "Artistas",
            "Hermanos",
            "Familias",
            "Social Issues",
            "Love & Romance",
            "Young adult literature",
            "Children's stories",
            "Siblings",
            "Death & Dying",
            "LGBTQ young adult",
            "Stonewall Book Awards",
            "nyt:young-adult=2014-10-05",
            "New York Times bestseller",
            "New York Times reviewed",
            "collectionID:EanesChallenge",
            "Teenage artists",
            "Mothers",
            "Sibling rivalry",
            "Miscommunication",
            "Gay teenagers",
            "collectionID:bannedbooks",
            "Siblings, fiction"
        ],
        "authors": [
            "Jandy Nelson"
        ],
        "publish_year": 2014
    },
    {
        "title": "The Stepdaughter",
        "subject": [
            "Fiction",
            "Romance",
            "Stepfamilies",
            "Romans, nouvelles"
        ],
        "authors": [
            "Iris Bromige"
        ],
        "publish_year": 1966
    },
    {
        "title": "Hidden Sins",
        "subject": [
            "Fiction",
            "Romance",
            "Suspense",
            "Fiction, romance, suspense",
            "African Americans",
            "Man-woman relationships",
            "American literature"
        ],
        "authors": [
            "Selena Montgomery"
        ],
        "publish_year": 2006
    },
    {
        "title": "Novels (Dance to the Piper / Last Honest Woman)",
        "subject": [
            "Biographers",
            "Women dancers",
            "Triplets",
            "Hurley family",
            "Fiction",
            "Businessmen",
            "Automobile racing drivers' spouses",
            "Widows",
            "Love stories, American",
            "Fiction, romance, contemporary",
            "Fiction, sagas",
            "Large type books",
            "Man-woman relationships",
            "Journalists",
            "Dancers",
            "Widows, fiction",
            "Romance",
            "nyt:mass-market-paperback=2010-10-31",
            "New York Times bestseller"
        ],
        "authors": [
            "Nora Roberts"
        ],
        "publish_year": 2004
    },
    {
        "title": "Our Souls at Night",
        "subject": [
            "Widowers",
            "Fiction",
            "Loneliness",
            "Grandparent and child",
            "Memory",
            "Romance fiction",
            "Domestic fiction",
            "Large type books",
            "Colorado, fiction",
            "Fiction, romance, general",
            "FICTION / Family Life",
            "FICTION / Romance / General",
            "FICTION / Literary",
            "Older people",
            "Widows",
            "Fellowship",
            "Family life",
            "Grief",
            "Emotions",
            "Romance",
            "General",
            "Literary",
            "nyt:hardcover-fiction=2015-06-14",
            "New York Times bestseller",
            "New York Times reviewed",
            "Fiction, family life",
            "Fiction, romance, contemporary",
            "Widowers, fiction",
            "Man-woman relationships, fiction",
            "Fiction, family life, general",
            "(Produktform)Hardback",
            "Alter",
            "Amerika",
            "Amerikaner",
            "Bewegend",
            "Colorado",
            "Einsamkeit",
            "Enkel",
            "Fonda, Jane",
            "Gespra\u0308che",
            "Holt",
            "Hunde",
            "Kind",
            "Klatschmohnfrau",
            "Kleinstadt",
            "Lehrer",
            "Liebe",
            "Liebesgeschichte",
            "Redford, Robert",
            "Senioren",
            "Stoner",
            "USA",
            "Verfilmung",
            "amerikanische Literatur",
            "best agers",
            "spa\u0308te",
            "A\u0308lterwerden",
            "(VLB-WN)1112: Hardcover, Softcover / Belletristik/Gegenwartsliteratur (ab 1945)"
        ],
        "authors": [
            "Kent Haruf"
        ],
        "publish_year": 2015
    },
    {
        "title": "Novels (Jane Eyre / Tenant of Wildfell Hall / Wuthering Heights)",
        "subject": [
            "British and irish fiction (fictional works by one author)",
            "Chang pian xiao shuo",
            "Children's fiction",
            "Classic fiction",
            "Classic Literature",
            "Country homes",
            "Country life",
            "Country life in fiction",
            "Cousins",
            "Cuentos de amor",
            "death",
            "Drama",
            "English language",
            "English language readers",
            "English literature: texts",
            "Families",
            "Ficci\u00f3n",
            "Fiction",
            "family life",
            "romance",
            "Foundlings",
            "Historical Fiction",
            "Inheritance and succession",
            "Interpersonal relations",
            "Landscape in literature",
            "love",
            "Man-woman relationships",
            "Manners and customs",
            "orphans",
            "Psychological fiction",
            "Reading Level-Grade 7",
            "Reading Level-Grade 8",
            "Reading Level-Grade 9",
            "Reading Level-Grade 10",
            "Reading Level-Grade 11",
            "Reading Level-Grade 12",
            "Rejection (Psychology)",
            "Relaciones hombre-mujer",
            "revenge",
            "Romance fiction",
            "romantic fiction",
            "Rural families",
            "slavery",
            "Social life and customs",
            "tragedy",
            "Triangles (Interpersonal relations)",
            "Young women",
            "English fiction",
            "Women authors",
            "Heathcliff (Fictitious character : Brontee)",
            "Edward Fairfax Rochester (Fictitious character)",
            "English literature (collections), 19th century"
        ],
        "authors": [
            "Anne Bront\u00eb",
            "Charlotte Bronte\u0308",
            "Emily Bronte\u0308"
        ],
        "publish_year": 1982
    },
    {
        "title": "Demelza",
        "subject": [
            "Ross Poldark (Fictitious character)",
            "Open Library Staff Picks",
            "Fiction",
            "Romance",
            "History",
            "Large type books",
            "English Historical fiction",
            "Fiction, historical, general",
            "Poldark, ross (fictitious character), fiction",
            "Cornwall (england : county), fiction",
            "Historical fiction, English",
            "Cornwall (England) -- Fiction"
        ],
        "authors": [
            "Winston Graham"
        ],
        "publish_year": 1953
    },
    {
        "title": "I'll Give You the Sun",
        "subject": [
            "Romance",
            "Young Adult",
            "Glbt",
            "Contemporary",
            "Fiction",
            "Coming of Age",
            "Death",
            "Families",
            "Brothers and sisters",
            "Juvenile fiction",
            "Family life",
            "Grief",
            "Twins",
            "Artists",
            "Gays",
            "Children's fiction",
            "Artists, fiction",
            "Twins, fiction",
            "Brothers and sisters, fiction",
            "Grief, fiction",
            "Death, fiction",
            "Family life, fiction",
            "California, fiction",
            "Homosexuality, fiction",
            "Mellizas",
            "Ficci\u00f3n juvenil",
            "Pena",
            "Muerte",
            "Artistas",
            "Hermanos",
            "Familias",
            "Social Issues",
            "Love & Romance",
            "Young adult literature",
            "Children's stories",
            "Siblings",
            "Death & Dying",
            "LGBTQ young adult",
            "Stonewall Book Awards",
            "nyt:young-adult=2014-10-05",
            "New York Times bestseller",
            "New York Times reviewed",
            "collectionID:EanesChallenge",
            "Teenage artists",
            "Mothers",
            "Sibling rivalry",
            "Miscommunication",
            "Gay teenagers",
            "collectionID:bannedbooks",
            "Siblings, fiction"
        ],
        "authors": [
            "Jandy Nelson"
        ],
        "publish_year": 2014
    },
    {
        "title": "The Stepdaughter",
        "subject": [
            "Fiction",
            "Romance",
            "Stepfamilies",
            "Romans, nouvelles"
        ],
        "authors": [
            "Iris Bromige"
        ],
        "publish_year": 1966
    },
    {
        "title": "Hidden Sins",
        "subject": [
            "Fiction",
            "Romance",
            "Suspense",
            "Fiction, romance, suspense",
            "African Americans",
            "Man-woman relationships",
            "American literature"
        ],
        "authors": [
            "Selena Montgomery"
        ],
        "publish_year": 2006
    },
    {
        "title": "Juliet takes a breath",
        "subject": [
            "Gays",
            "Gays' writings, American",
            "Fiction",
            "Children's fiction",
            "Lesbians, fiction",
            "Fiction, coming of age",
            "Lesbians",
            "Puerto Ricans",
            "Feminism",
            "Authors",
            "Prejudices",
            "Internship programs",
            "Coming-of-age",
            "Lesbiennes",
            "Romans, nouvelles",
            "Juvenile fiction",
            "Employees",
            "Training",
            "Adolescence",
            "Puerto Rican lesbians",
            "Homosexuels",
            "Romans, nouvelles, etc. pour la jeunesse",
            "YOUNG ADULT FICTION / Coming of Age",
            "Young Adult Fiction",
            "Romance",
            "Young Adult Literature",
            "collectionID:bannedbooks"
        ],
        "authors": [
            "Gabby Rivera",
            "Gaby Rivera"
        ],
        "publish_year": 2016
    },
    {
        "title": "The Lies We Told",
        "subject": [
            "Fiction",
            "Relationship Novel",
            "Romance",
            "Sisters",
            "Murder victims' families",
            "Crimes against",
            "Sisters, fiction",
            "North carolina, fiction",
            "Fiction, family life",
            "Women physicians, fiction",
            "Fiction, general",
            "Women physicians",
            "Family secrets",
            "Hurricanes",
            "Fiction, family life, general"
        ],
        "authors": [
            "Diane Chamberlain"
        ],
        "publish_year": 2010
    },
    {
        "title": "Last Breath",
        "subject": [
            "Fiction",
            "Romance",
            "Archaeological thefts",
            "Fiction, romance, suspense"
        ],
        "authors": [
            "Mariah Stewart"
        ],
        "publish_year": 2007
    },
    {
        "title": "Blood Red",
        "subject": [
            "Vampires",
            "Paranormal",
            "Fiction",
            "Romance",
            "Fantasy",
            "Fiction, romance, paranormal",
            "New orleans (la.), fiction",
            "Vampires, fiction",
            "Large type books",
            "Fiction, romance, paranormal, general",
            "Fiction, romance, fantasy",
            "Fiction, romance, suspense",
            "Fiction, romance, contemporary"
        ],
        "authors": [
            "Heather Graham"
        ],
        "publish_year": 2007
    },
    {
        "title": "Reckless",
        "subject": [
            "Fiction",
            "Orphans",
            "Romance",
            "Women lawyers",
            "Man-woman relationships",
            "African Americans",
            "African American women lawyers",
            "Fiction, romance, historical, general"
        ],
        "authors": [
            "Selena Montgomery"
        ],
        "publish_year": 2008
    },
    {
        "title": "The Stepdaughter",
        "subject": [
            "Fiction",
            "Romance",
            "Stepfamilies",
            "Romans, nouvelles"
        ],
        "authors": [
            "Iris Bromige"
        ],
        "publish_year": 1966
    },
    {
        "title": "Hidden Sins",
        "subject": [
            "Fiction",
            "Romance",
            "Suspense",
            "Fiction, romance, suspense",
            "African Americans",
            "Man-woman relationships",
            "American literature"
        ],
        "authors": [
            "Selena Montgomery"
        ],
        "publish_year": 2006
    },
    {
        "title": "Juliet takes a breath",
        "subject": [
            "Gays",
            "Gays' writings, American",
            "Fiction",
            "Children's fiction",
            "Lesbians, fiction",
            "Fiction, coming of age",
            "Lesbians",
            "Puerto Ricans",
            "Feminism",
            "Authors",
            "Prejudices",
            "Internship programs",
            "Coming-of-age",
            "Lesbiennes",
            "Romans, nouvelles",
            "Juvenile fiction",
            "Employees",
            "Training",
            "Adolescence",
            "Puerto Rican lesbians",
            "Homosexuels",
            "Romans, nouvelles, etc. pour la jeunesse",
            "YOUNG ADULT FICTION / Coming of Age",
            "Young Adult Fiction",
            "Romance",
            "Young Adult Literature",
            "collectionID:bannedbooks"
        ],
        "authors": [
            "Gabby Rivera",
            "Gaby Rivera"
        ],
        "publish_year": 2016
    },
    {
        "title": "The Lies We Told",
        "subject": [
            "Fiction",
            "Relationship Novel",
            "Romance",
            "Sisters",
            "Murder victims' families",
            "Crimes against",
            "Sisters, fiction",
            "North carolina, fiction",
            "Fiction, family life",
            "Women physicians, fiction",
            "Fiction, general",
            "Women physicians",
            "Family secrets",
            "Hurricanes",
            "Fiction, family life, general"
        ],
        "authors": [
            "Diane Chamberlain"
        ],
        "publish_year": 2010
    },
    {
        "title": "Last Breath",
        "subject": [
            "Fiction",
            "Romance",
            "Archaeological thefts",
            "Fiction, romance, suspense"
        ],
        "authors": [
            "Mariah Stewart"
        ],
        "publish_year": 2007
    },
    {
        "title": "Blood Red",
        "subject": [
            "Vampires",
            "Paranormal",
            "Fiction",
            "Romance",
            "Fantasy",
            "Fiction, romance, paranormal",
            "New orleans (la.), fiction",
            "Vampires, fiction",
            "Large type books",
            "Fiction, romance, paranormal, general",
            "Fiction, romance, fantasy",
            "Fiction, romance, suspense",
            "Fiction, romance, contemporary"
        ],
        "authors": [
            "Heather Graham"
        ],
        "publish_year": 2007
    },
    {
        "title": "Reckless",
        "subject": [
            "Fiction",
            "Orphans",
            "Romance",
            "Women lawyers",
            "Man-woman relationships",
            "African Americans",
            "African American women lawyers",
            "Fiction, romance, historical, general"
        ],
        "authors": [
            "Selena Montgomery"
        ],
        "publish_year": 2008
    },
    {
        "title": "Partners",
        "subject": [
            "Romance",
            "Journalists",
            "Contemporary",
            "Fiction",
            "1980s",
            "Women journalists",
            "Love stories, American",
            "Large type books",
            "Women journalists, fiction",
            "Fiction, romance, contemporary",
            "Contemporary Fiction",
            "Romance Fiction",
            "Fiction, romance, general",
            "Man-woman relationships, fiction",
            "Fiction, romance, suspense",
            "New orleans (la.), fiction",
            "Crime, fiction",
            "Murder",
            "Investigation"
        ],
        "authors": [
            "Nora Roberts"
        ],
        "publish_year": 1985
    },
    {
        "title": "The Playboy Boss's Chosen Bride",
        "subject": [
            "Fiction, romance, general",
            "Man-woman relationships",
            "Fiction",
            "Romance",
            "Passion",
            "Large type books",
            "Romance fiction"
        ],
        "authors": [
            "Emma Darcy"
        ],
        "publish_year": 2006
    },
    {
        "title": "Mercy Street",
        "subject": [
            "Rich people",
            "Fiction",
            "Romance",
            "Loss (Psychology)",
            "Investigation",
            "Businessmen",
            "Missing persons",
            "Large type books"
        ],
        "authors": [
            "Mariah Stewart"
        ],
        "publish_year": 2008
    },
    {
        "title": "Hitts & Mrs",
        "subject": [
            "Fiction",
            "Romance",
            "Married people, fiction",
            "New york (n.y.), fiction",
            "Connecticut, fiction",
            "Fiction, romance, general",
            "Triangles (Interpersonal relations",
            "Married people",
            "Architects",
            "Women interior decorators",
            "Fiction, romance, contemporary"
        ],
        "authors": [
            "Lori Bryant-Woolridge"
        ],
        "publish_year": 2004
    },
    {
        "title": "For the Love of Lilah",
        "subject": [
            "1990s",
            "Contemporary",
            "Romance",
            "Fiction",
            "Storms",
            "Rescues",
            "The Calhoun Women",
            "Large type books",
            "Love stories, American",
            "Fiction, general",
            "Rescues in fiction",
            "Storms in fiction",
            "Fiction, romance, general",
            "Fiction, romance, historical",
            "Fiction, romance, historical, general",
            "Man-woman relationships"
        ],
        "authors": [
            "Nora Roberts"
        ],
        "publish_year": 1991
    },
    {
        "title": "Blood Red",
        "subject": [
            "Vampires",
            "Paranormal",
            "Fiction",
            "Romance",
            "Fantasy",
            "Fiction, romance, paranormal",
            "New orleans (la.), fiction",
            "Vampires, fiction",
            "Large type books",
            "Fiction, romance, paranormal, general",
            "Fiction, romance, fantasy",
            "Fiction, romance, suspense",
            "Fiction, romance, contemporary"
        ],
        "authors": [
            "Heather Graham"
        ],
        "publish_year": 2007
    },
    {
        "title": "Reckless",
        "subject": [
            "Fiction",
            "Orphans",
            "Romance",
            "Women lawyers",
            "Man-woman relationships",
            "African Americans",
            "African American women lawyers",
            "Fiction, romance, historical, general"
        ],
        "authors": [
            "Selena Montgomery"
        ],
        "publish_year": 2008
    },
    {
        "title": "Partners",
        "subject": [
            "Romance",
            "Journalists",
            "Contemporary",
            "Fiction",
            "1980s",
            "Women journalists",
            "Love stories, American",
            "Large type books",
            "Women journalists, fiction",
            "Fiction, romance, contemporary",
            "Contemporary Fiction",
            "Romance Fiction",
            "Fiction, romance, general",
            "Man-woman relationships, fiction",
            "Fiction, romance, suspense",
            "New orleans (la.), fiction",
            "Crime, fiction",
            "Murder",
            "Investigation"
        ],
        "authors": [
            "Nora Roberts"
        ],
        "publish_year": 1985
    },
    {
        "title": "The Playboy Boss's Chosen Bride",
        "subject": [
            "Fiction, romance, general",
            "Man-woman relationships",
            "Fiction",
            "Romance",
            "Passion",
            "Large type books",
            "Romance fiction"
        ],
        "authors": [
            "Emma Darcy"
        ],
        "publish_year": 2006
    },
    {
        "title": "Mercy Street",
        "subject": [
            "Rich people",
            "Fiction",
            "Romance",
            "Loss (Psychology)",
            "Investigation",
            "Businessmen",
            "Missing persons",
            "Large type books"
        ],
        "authors": [
            "Mariah Stewart"
        ],
        "publish_year": 2008
    },
    {
        "title": "Hitts & Mrs",
        "subject": [
            "Fiction",
            "Romance",
            "Married people, fiction",
            "New york (n.y.), fiction",
            "Connecticut, fiction",
            "Fiction, romance, general",
            "Triangles (Interpersonal relations",
            "Married people",
            "Architects",
            "Women interior decorators",
            "Fiction, romance, contemporary"
        ],
        "authors": [
            "Lori Bryant-Woolridge"
        ],
        "publish_year": 2004
    },
    {
        "title": "For the Love of Lilah",
        "subject": [
            "1990s",
            "Contemporary",
            "Romance",
            "Fiction",
            "Storms",
            "Rescues",
            "The Calhoun Women",
            "Large type books",
            "Love stories, American",
            "Fiction, general",
            "Rescues in fiction",
            "Storms in fiction",
            "Fiction, romance, general",
            "Fiction, romance, historical",
            "Fiction, romance, historical, general",
            "Man-woman relationships"
        ],
        "authors": [
            "Nora Roberts"
        ],
        "publish_year": 1991
    },
    {
        "title": "The Greek's Bought Wife",
        "subject": [
            "Romance",
            "Passion",
            "Fiction",
            "Fiction, romance, general"
        ],
        "authors": [
            "Helen Bianchin"
        ],
        "publish_year": 2005
    },
    {
        "title": "The Greek Tycoon's Virgin Wife",
        "subject": [
            "Fiction",
            "Passion",
            "Romance",
            "Fiction, romance, general",
            "Socialites",
            "Greeks",
            "Virginity",
            "Arranged marriage"
        ],
        "authors": [
            "Helen Bianchin"
        ],
        "publish_year": 2007
    },
    {
        "title": "Beguiled",
        "subject": [
            "Romance",
            "Historical Romance",
            "Historical Fiction",
            "Fiction",
            "Fiction, romance, historical",
            "London (england), fiction",
            "Fiction, romance, suspense",
            "Large type books",
            "Man-woman relationships",
            "Fiction, romance, historical, general"
        ],
        "authors": [
            "Heather Graham"
        ],
        "publish_year": 2006
    },
    {
        "title": "Expecting the Playboy's Heir",
        "subject": [
            "Fiction, Romance, Contemporary",
            "Fiction, romance, general",
            "Fiction",
            "Romance",
            "Contemporary\"",
            "Passion"
        ],
        "authors": [
            "Penny Jordan"
        ],
        "publish_year": 2005
    },
    {
        "title": "Duty, Desire and the Desert King",
        "subject": [
            "Fiction",
            "Romance",
            "Contemporary",
            "Passion",
            "OverDrive",
            "Man-woman relationships",
            "Kings and rulers",
            "Seduction",
            "Arabs",
            "a, Cuentos de amor, Relaciones hombre-mujer, \u00c1rabes, Novela, Reyes y soberanos, Estupro, Fiction",
            "erotica\"",
            "Fiction, romance, general",
            "Sultans",
            "Desire",
            "Interpersonal attraction",
            "\u00c1rabes",
            "Novela",
            "Reyes y soberanos",
            "Deseo",
            "Estupro",
            "FICTION",
            "Atracciones interpersonales",
            "Relaciones hombre-mujer"
        ],
        "authors": [
            "Jane Porter"
        ],
        "publish_year": 2009
    },
    {
        "title": "Hitts & Mrs",
        "subject": [
            "Fiction",
            "Romance",
            "Married people, fiction",
            "New york (n.y.), fiction",
            "Connecticut, fiction",
            "Fiction, romance, general",
            "Triangles (Interpersonal relations",
            "Married people",
            "Architects",
            "Women interior decorators",
            "Fiction, romance, contemporary"
        ],
        "authors": [
            "Lori Bryant-Woolridge"
        ],
        "publish_year": 2004
    },
    {
        "title": "For the Love of Lilah",
        "subject": [
            "1990s",
            "Contemporary",
            "Romance",
            "Fiction",
            "Storms",
            "Rescues",
            "The Calhoun Women",
            "Large type books",
            "Love stories, American",
            "Fiction, general",
            "Rescues in fiction",
            "Storms in fiction",
            "Fiction, romance, general",
            "Fiction, romance, historical",
            "Fiction, romance, historical, general",
            "Man-woman relationships"
        ],
        "authors": [
            "Nora Roberts"
        ],
        "publish_year": 1991
    },
    {
        "title": "The Greek's Bought Wife",
        "subject": [
            "Romance",
            "Passion",
            "Fiction",
            "Fiction, romance, general"
        ],
        "authors": [
            "Helen Bianchin"
        ],
        "publish_year": 2005
    },
    {
        "title": "The Greek Tycoon's Virgin Wife",
        "subject": [
            "Fiction",
            "Passion",
            "Romance",
            "Fiction, romance, general",
            "Socialites",
            "Greeks",
            "Virginity",
            "Arranged marriage"
        ],
        "authors": [
            "Helen Bianchin"
        ],
        "publish_year": 2007
    },
    {
        "title": "Beguiled",
        "subject": [
            "Romance",
            "Historical Romance",
            "Historical Fiction",
            "Fiction",
            "Fiction, romance, historical",
            "London (england), fiction",
            "Fiction, romance, suspense",
            "Large type books",
            "Man-woman relationships",
            "Fiction, romance, historical, general"
        ],
        "authors": [
            "Heather Graham"
        ],
        "publish_year": 2006
    },
    {
        "title": "Expecting the Playboy's Heir",
        "subject": [
            "Fiction, Romance, Contemporary",
            "Fiction, romance, general",
            "Fiction",
            "Romance",
            "Contemporary\"",
            "Passion"
        ],
        "authors": [
            "Penny Jordan"
        ],
        "publish_year": 2005
    },
    {
        "title": "Duty, Desire and the Desert King",
        "subject": [
            "Fiction",
            "Romance",
            "Contemporary",
            "Passion",
            "OverDrive",
            "Man-woman relationships",
            "Kings and rulers",
            "Seduction",
            "Arabs",
            "a, Cuentos de amor, Relaciones hombre-mujer, \u00c1rabes, Novela, Reyes y soberanos, Estupro, Fiction",
            "erotica\"",
            "Fiction, romance, general",
            "Sultans",
            "Desire",
            "Interpersonal attraction",
            "\u00c1rabes",
            "Novela",
            "Reyes y soberanos",
            "Deseo",
            "Estupro",
            "FICTION",
            "Atracciones interpersonales",
            "Relaciones hombre-mujer"
        ],
        "authors": [
            "Jane Porter"
        ],
        "publish_year": 2009
    },
    {
        "title": "Burn",
        "subject": [
            "Fiction",
            "Romantic suspense",
            "Romance",
            "Ocean travel",
            "Lottery winners",
            "Cruise ships",
            "Hostages",
            "New York Times bestseller",
            "Large type books",
            "Fiction, romance, suspense"
        ],
        "authors": [
            "Linda Howard"
        ],
        "publish_year": 2009
    },
    {
        "title": "Crossing Brooklyn Ferry",
        "subject": [
            "Drama",
            "Fiction",
            "Romance",
            "New York Times reviewed",
            "New york (n.y.), fiction",
            "Fiction, romance, contemporary",
            "Man-woman relationships, fiction"
        ],
        "authors": [
            "Jennie Fields"
        ],
        "publish_year": 1997
    },
    {
        "title": "Between friends",
        "subject": [
            "Correspondence",
            "Married women",
            "Relationship Novel",
            "Women lawyers",
            "Fiction",
            "Romance",
            "Female friendship",
            "Women",
            "Fiction, romance, contemporary",
            "Friendship, fiction",
            "New york (n.y.), fiction",
            "Washington (state), fiction",
            "United states, fiction",
            "Fiction, general",
            "Large type books",
            "Friendship",
            "Fiction, romance, general",
            "Married people, fiction",
            "Women lawyers, fiction"
        ],
        "authors": [
            "Debbie Macomber",
            "JoAnn Ross"
        ],
        "publish_year": 2002
    },
    {
        "title": "The Contaxis Baby",
        "subject": [
            "Fiction, romance, general",
            "Fiction",
            "Romance",
            "Contemporary",
            "Harlequin",
            "Pregnancy",
            "Greeks",
            "Greek billionaires",
            "Fiction, Romance, Contemporary"
        ],
        "authors": [
            "Lynne Graham"
        ],
        "publish_year": 2002
    },
    {
        "title": "Dinner first, me later?",
        "subject": [
            "Baseball players",
            "Divorced women",
            "Fiction",
            "Romance",
            "Single fathers",
            "Fiction, romance, general",
            "Baseball players, fiction",
            "Divorced people, fiction"
        ],
        "authors": [
            "Candy Halliday"
        ],
        "publish_year": 2007
    },
    {
        "title": "Expecting the Playboy's Heir",
        "subject": [
            "Fiction, Romance, Contemporary",
            "Fiction, romance, general",
            "Fiction",
            "Romance",
            "Contemporary\"",
            "Passion"
        ],
        "authors": [
            "Penny Jordan"
        ],
        "publish_year": 2005
    },
    {
        "title": "Duty, Desire and the Desert King",
        "subject": [
            "Fiction",
            "Romance",
            "Contemporary",
            "Passion",
            "OverDrive",
            "Man-woman relationships",
            "Kings and rulers",
            "Seduction",
            "Arabs",
            "a, Cuentos de amor, Relaciones hombre-mujer, \u00c1rabes, Novela, Reyes y soberanos, Estupro, Fiction",
            "erotica\"",
            "Fiction, romance, general",
            "Sultans",
            "Desire",
            "Interpersonal attraction",
            "\u00c1rabes",
            "Novela",
            "Reyes y soberanos",
            "Deseo",
            "Estupro",
            "FICTION",
            "Atracciones interpersonales",
            "Relaciones hombre-mujer"
        ],
        "authors": [
            "Jane Porter"
        ],
        "publish_year": 2009
    },
    {
        "title": "Burn",
        "subject": [
            "Fiction",
            "Romantic suspense",
            "Romance",
            "Ocean travel",
            "Lottery winners",
            "Cruise ships",
            "Hostages",
            "New York Times bestseller",
            "Large type books",
            "Fiction, romance, suspense"
        ],
        "authors": [
            "Linda Howard"
        ],
        "publish_year": 2009
    },
    {
        "title": "Crossing Brooklyn Ferry",
        "subject": [
            "Drama",
            "Fiction",
            "Romance",
            "New York Times reviewed",
            "New york (n.y.), fiction",
            "Fiction, romance, contemporary",
            "Man-woman relationships, fiction"
        ],
        "authors": [
            "Jennie Fields"
        ],
        "publish_year": 1997
    },
    {
        "title": "Between friends",
        "subject": [
            "Correspondence",
            "Married women",
            "Relationship Novel",
            "Women lawyers",
            "Fiction",
            "Romance",
            "Female friendship",
            "Women",
            "Fiction, romance, contemporary",
            "Friendship, fiction",
            "New york (n.y.), fiction",
            "Washington (state), fiction",
            "United states, fiction",
            "Fiction, general",
            "Large type books",
            "Friendship",
            "Fiction, romance, general",
            "Married people, fiction",
            "Women lawyers, fiction"
        ],
        "authors": [
            "Debbie Macomber",
            "JoAnn Ross"
        ],
        "publish_year": 2002
    },
    {
        "title": "The Contaxis Baby",
        "subject": [
            "Fiction, romance, general",
            "Fiction",
            "Romance",
            "Contemporary",
            "Harlequin",
            "Pregnancy",
            "Greeks",
            "Greek billionaires",
            "Fiction, Romance, Contemporary"
        ],
        "authors": [
            "Lynne Graham"
        ],
        "publish_year": 2002
    },
    {
        "title": "Dinner first, me later?",
        "subject": [
            "Baseball players",
            "Divorced women",
            "Fiction",
            "Romance",
            "Single fathers",
            "Fiction, romance, general",
            "Baseball players, fiction",
            "Divorced people, fiction"
        ],
        "authors": [
            "Candy Halliday"
        ],
        "publish_year": 2007
    },
    {
        "title": "Deadly harvest",
        "subject": [
            "Romance",
            "Murder",
            "Police",
            "Serial murders",
            "Paranormal",
            "Crimes against",
            "Fiction",
            "Fantasy",
            "Investigation",
            "Missing persons",
            "Women",
            "Fiction, romance, suspense",
            "Fiction, romance, paranormal",
            "Serial murders, fiction",
            "Salem (mass.), fiction",
            "Crime, fiction",
            "Fiction, ghost",
            "Fiction, occult & supernatural",
            "Large type books",
            "nyt:mass-market-paperback=2008-11-16",
            "New York Times bestseller",
            "Fiction, romance, paranormal, general",
            "Fiction, mystery & detective, police procedural"
        ],
        "authors": [
            "Heather Graham",
            "Phil Gigante"
        ],
        "publish_year": 2008
    },
    {
        "title": "Burning Wild",
        "subject": [
            "Fiction",
            "Rich people",
            "Nannies",
            "Romance",
            "Large type books",
            "Fiction, romance, erotic",
            "Interpersonal attraction",
            "nyt:mass-market-paperback=2009-05-17",
            "New York Times bestseller",
            "Fiction, romance, paranormal, general",
            "Fiction, romance, paranormal"
        ],
        "authors": [
            "Christine Feehan",
            "Jeff Cummings"
        ],
        "publish_year": 2009
    },
    {
        "title": "Mad is the heart",
        "subject": [
            "1960s",
            "Contemporary",
            "English",
            "Fiction",
            "Love Triangle",
            "Romance"
        ],
        "authors": [
            "Denise Robins"
        ],
        "publish_year": 1963
    },
    {
        "title": "Lucky's Lady",
        "subject": [
            "Fiction",
            "Romance",
            "Large type books",
            "Swamps",
            "Missing persons",
            "Cajuns",
            "Fiction, romance, contemporary",
            "Louisiana, fiction"
        ],
        "authors": [
            "Tami Hoag"
        ],
        "publish_year": 1992
    },
    {
        "title": "The Monk Upstairs",
        "subject": [
            "Fiction",
            "Romance",
            "Ex-monks",
            "Single mothers",
            "Landlord and tenant",
            "California, fiction",
            "Fiction, romance, general"
        ],
        "authors": [
            "Tim Farrington"
        ],
        "publish_year": 2007
    },
    {
        "title": "The Contaxis Baby",
        "subject": [
            "Fiction, romance, general",
            "Fiction",
            "Romance",
            "Contemporary",
            "Harlequin",
            "Pregnancy",
            "Greeks",
            "Greek billionaires",
            "Fiction, Romance, Contemporary"
        ],
        "authors": [
            "Lynne Graham"
        ],
        "publish_year": 2002
    },
    {
        "title": "Dinner first, me later?",
        "subject": [
            "Baseball players",
            "Divorced women",
            "Fiction",
            "Romance",
            "Single fathers",
            "Fiction, romance, general",
            "Baseball players, fiction",
            "Divorced people, fiction"
        ],
        "authors": [
            "Candy Halliday"
        ],
        "publish_year": 2007
    },
    {
        "title": "Deadly harvest",
        "subject": [
            "Romance",
            "Murder",
            "Police",
            "Serial murders",
            "Paranormal",
            "Crimes against",
            "Fiction",
            "Fantasy",
            "Investigation",
            "Missing persons",
            "Women",
            "Fiction, romance, suspense",
            "Fiction, romance, paranormal",
            "Serial murders, fiction",
            "Salem (mass.), fiction",
            "Crime, fiction",
            "Fiction, ghost",
            "Fiction, occult & supernatural",
            "Large type books",
            "nyt:mass-market-paperback=2008-11-16",
            "New York Times bestseller",
            "Fiction, romance, paranormal, general",
            "Fiction, mystery & detective, police procedural"
        ],
        "authors": [
            "Heather Graham",
            "Phil Gigante"
        ],
        "publish_year": 2008
    },
    {
        "title": "Burning Wild",
        "subject": [
            "Fiction",
            "Rich people",
            "Nannies",
            "Romance",
            "Large type books",
            "Fiction, romance, erotic",
            "Interpersonal attraction",
            "nyt:mass-market-paperback=2009-05-17",
            "New York Times bestseller",
            "Fiction, romance, paranormal, general",
            "Fiction, romance, paranormal"
        ],
        "authors": [
            "Christine Feehan",
            "Jeff Cummings"
        ],
        "publish_year": 2009
    },
    {
        "title": "Mad is the heart",
        "subject": [
            "1960s",
            "Contemporary",
            "English",
            "Fiction",
            "Love Triangle",
            "Romance"
        ],
        "authors": [
            "Denise Robins"
        ],
        "publish_year": 1963
    },
    {
        "title": "Lucky's Lady",
        "subject": [
            "Fiction",
            "Romance",
            "Large type books",
            "Swamps",
            "Missing persons",
            "Cajuns",
            "Fiction, romance, contemporary",
            "Louisiana, fiction"
        ],
        "authors": [
            "Tami Hoag"
        ],
        "publish_year": 1992
    },
    {
        "title": "The Monk Upstairs",
        "subject": [
            "Fiction",
            "Romance",
            "Ex-monks",
            "Single mothers",
            "Landlord and tenant",
            "California, fiction",
            "Fiction, romance, general"
        ],
        "authors": [
            "Tim Farrington"
        ],
        "publish_year": 2007
    },
    {
        "title": "Milkrun",
        "subject": [
            "Romance",
            "Chick Lit",
            "Fiction",
            "Single women",
            "Dating (Social customs)",
            "Fiction, romance, contemporary",
            "Boston (mass.), fiction",
            "Single women, fiction",
            "Dating (social customs), fiction",
            "JUVENILE FICTION",
            "General",
            "Zhang pian xiao shuo"
        ],
        "authors": [
            "Sarah Mlynowski"
        ],
        "publish_year": 2001
    },
    {
        "title": "The s\u00e9ance",
        "subject": [
            "Spiritualism",
            "Police",
            "Romantic suspense",
            "Serial murders",
            "Paranormal",
            "Fiction",
            "Romance",
            "Fantasy",
            "Ouija board",
            "Serial murderers",
            "Ouija boards",
            "Fiction, romance, fantasy",
            "Oui-ja",
            "Romans, nouvelles",
            "Tueurs en s\u00e9rie",
            "Large type books",
            "Fiction, occult & supernatural",
            "Fiction, horror",
            "Serial murders, fiction",
            "Florida, fiction"
        ],
        "authors": [
            "Heather Graham"
        ],
        "publish_year": 2007
    },
    {
        "title": "Spencer Brade M.D.",
        "subject": [
            "Vintage",
            "Adult",
            "American",
            "Fiction",
            "Literature",
            "Novel",
            "Hardcover",
            "Paperback",
            "e-book",
            "Adventure",
            "Contemporary",
            "Roman romance",
            "Romance",
            "Romantic",
            "Medical",
            "Physicians",
            "M.D.",
            "Doctor",
            "Sentiment",
            "Sentimental",
            "Pulp fiction",
            "universit\u00e9 am\u00e9ricaine"
        ],
        "authors": [
            "Frank G. Slaughter"
        ],
        "publish_year": 1942
    },
    {
        "title": "The red-hot Cajun",
        "subject": [
            "Abduction",
            "Fiction",
            "Romance",
            "Fiction, romance, general",
            "Large type books",
            "Fiction, romance, contemporary",
            "Louisiana, fiction"
        ],
        "authors": [
            "Sandra Hill"
        ],
        "publish_year": 2005
    },
    {
        "title": "Low country",
        "subject": [
            "Fiction",
            "Islands",
            "Married women",
            "Nature conservation",
            "Real estate developers",
            "Real estate development",
            "Romance",
            "Family life",
            "Fiction, general",
            "South carolina, fiction",
            "Large type books"
        ],
        "authors": [
            "Anne Rivers Siddons"
        ],
        "publish_year": 1998
    }
]